__init__.py
config/__init__.py
config/default_headers.py
tidyxbrl/__init__.py
tidyxbrl/edgar_cik.py
tidyxbrl/edgar_frames.py
tidyxbrl/edgar_query.py
tidyxbrl/xbrl_apikey.py
tidyxbrl/xbrl_parse.py
tidyxbrl/xbrl_query.py
tidyxbrl-1.2.13.dist-info/LICENSE
tidyxbrl-1.2.13.dist-info/METADATA
tidyxbrl-1.2.13.dist-info/WHEEL
tidyxbrl-1.2.13.dist-info/top_level.txt
tidyxbrl-1.2.13.dist-info/RECORD
