Metadata-Version: 2.1
Name: tidyxbrl
Version: 1.2.13
Summary: A python package to parse the XBRL file format & interface with XBRL APIs in a tidy format. A powerful tool for automated financial analysis, accounting, and investment research using Pandas.
Author-email: Ryan McDonald <ryancmcdonald@gmail.com>
Project-URL: Homepage, https://github.com/cowboycodeman/tidyxbrl/
Project-URL: Issues, https://github.com/cowboycodeman/tidyxbrl/issues
Classifier: Programming Language :: Python :: 3
Classifier: License :: OSI Approved :: MIT License
Classifier: Operating System :: OS Independent
Classifier: Development Status :: 4 - Beta
Classifier: Intended Audience :: Developers
Classifier: Intended Audience :: Financial and Insurance Industry
Classifier: Topic :: Office/Business :: Financial :: Investment
Classifier: Topic :: Office/Business :: Financial :: Accounting
Classifier: Natural Language :: English
Requires-Python: <3.12,>=3.9
License-File: LICENSE
Requires-Dist: beautifulsoup4==4.11.2
Requires-Dist: bs4==0.0.1
Requires-Dist: certifi==2023.7.22
Requires-Dist: charset-normalizer==3.0.1
Requires-Dist: idna==3.7
Requires-Dist: numpy==1.24.2
Requires-Dist: pandas==1.5.3
Requires-Dist: python-dateutil==2.8.2
Requires-Dist: pytz==2022.7.1
Requires-Dist: requests==2.32.2
Requires-Dist: six==1.16.0
Requires-Dist: soupsieve==2.4
Requires-Dist: tqdm==4.66.3
Requires-Dist: urllib3==1.26.18
Requires-Dist: PyYAML>=5.4.1
Requires-Dist: lxml>=4.9.2
Requires-Dist: tidyxbrl>=1.0.2
Requires-Dist: httpx>=0.27.0
